setup.cfg
setup.py
wpsync/__init__.py
wpsync/__main__.py
wpsync/wpsync.py
wpsync.egg-info/PKG-INFO
wpsync.egg-info/SOURCES.txt
wpsync.egg-info/dependency_links.txt
wpsync.egg-info/entry_points.txt
wpsync.egg-info/top_level.txt