Metadata-Version: 1.1
Name: wpsync
Version: 1.0.1
Summary: A tool to sync the WordPress SVN with your Git (or SVN) repository.
Home-page: https://github.com/refactors/wpsync
Author: Henrique
Author-email: hacdias@gmail.com
License: UNKNOWN
Keywords: wordpress,svn,git,sync
Platform: any
Classifier: Programming Language :: Python
Classifier: Programming Language :: Python :: 3
Classifier: Programming Language :: Python :: 3 :: Only
Classifier: License :: OSI Approved :: GNU Library or Lesser General Public License (LGPL)
Classifier: Operating System :: OS Independent
Classifier: Environment :: Console
Classifier: Natural Language :: English
Classifier: Topic :: Software Development :: Version Control
Classifier: Topic :: Software Development :: Build Tools
Classifier: Topic :: Utilities
